scopes/__init__.py
scopes/cli.py
scopes/scopes.py
scopes_py-0.1.1.dist-info/DESCRIPTION.rst
scopes_py-0.1.1.dist-info/METADATA
scopes_py-0.1.1.dist-info/RECORD
scopes_py-0.1.1.dist-info/WHEEL
scopes_py-0.1.1.dist-info/entry_points.txt
scopes_py-0.1.1.dist-info/metadata.json
scopes_py-0.1.1.dist-info/top_level.txt
